DESCRIPTION.rst
LICENSE.rst
MANIFEST.in
README.rst
kernel.py
setup.cfg
setup.py
doc/Makefile
doc/source/CSEMEdges.rst
doc/source/Contact.rst
doc/source/Download.rst
doc/source/Features.rst
doc/source/Installation.rst
doc/source/Manual.rst
doc/source/Publications.rst
doc/source/Tutorial.rst
doc/source/WhatIs.rst
doc/source/conf.py
doc/source/index.rst
doc/source/_downloads/BSD-3.pdf
doc/source/_downloads/case1.zip
doc/source/_downloads/case2.zip
doc/source/_downloads/case3.zip
doc/source/_downloads/kernel.py
doc/source/_downloads/params.yaml
doc/source/_downloads/petsc.opts
doc/source/_static/Documentation.rst~
doc/source/_static/Features.rst~
doc/source/_static/Tutorial.rst~
doc/source/_static/petgem.css
doc/source/_static/petgem.css~
doc/source/_static/setup.cfg
doc/source/_static/figures/PETGEM_assembly.png
doc/source/_static/figures/PETGEM_parallel_scheme.png
doc/source/_static/figures/class_diagram.png
doc/source/_static/figures/component_diagram.png
doc/source/_static/figures/edgeElement.jpg
doc/source/_static/figures/logo_bsc.jpeg
doc/source/_static/figures/model1.png
doc/source/_static/figures/model_preprocessing.png
doc/source/_static/figures/output_preprocessing.png
doc/source/_static/figures/petgem_logo.png
doc/source/_static/figures/sequence_diagram.png
doc/source/_static/figures/softwareStack.jpg
doc/source/_static/figures/totalFieldVTK.png
doc/source/_static/figures/total_field_X_model1.png
doc/source/_static/figures/total_field_X_model2.png
doc/source/_templates/layout.html
doc/source/petgem/common.rst
doc/source/petgem/hvfem.rst
doc/source/petgem/kernel.rst
doc/source/petgem/mesh.rst
doc/source/petgem/parallel.rst
doc/source/petgem/preprocessing.rst
doc/source/petgem/solver.rst
doc/source/petgem/vectors.rst
doc/source/petgem_theme/theme.conf
doc/source/petgem_theme/theme.conf~
examples/case1.zip
examples/case2.zip
examples/case3.zip
petgem/common.py
petgem/hvfem.py
petgem/mesh.py
petgem/parallel.py
petgem/preprocessing.py
petgem/solver.py
petgem.egg-info/PKG-INFO
petgem.egg-info/SOURCES.txt
petgem.egg-info/dependency_links.txt
petgem.egg-info/requires.txt
petgem.egg-info/top_level.txt