Metadata-Version: 1.2
Name: petgem
Version: 0.9
Summary: Parallel python code for electromagnetic modeling in geophysics using high-order nédélec finite elements
Home-page: https://www.bsc.es/castillo-octavio
Maintainer: Octavio Castillo-Reyes
Maintainer-email: octavio.castillo@bsc.es
License: BSD-3
Download-URL: http://petgem.bsc.es
Keywords: 3D CSEM, high-order edge finite elements, HPC, numerical simulation
Platform: Linux
Classifier: Development Status :: 3 - Alpha
Classifier: License :: Free for non-commercial use
Classifier: Intended Audience :: Science/Research
Classifier: Intended Audience :: Developers
Classifier: Programming Language :: Python :: 3.6
Classifier: Topic :: Scientific/Engineering
Classifier: Topic :: Software Development :: Libraries
Classifier: Operating System :: POSIX :: Linux
